pdf_generator/__init__.py
pdf_generator/image.py
pdf_generator/main.py
pdf_generator_aniket-2.1.1.dist-info/LICENSE
pdf_generator_aniket-2.1.1.dist-info/METADATA
pdf_generator_aniket-2.1.1.dist-info/WHEEL
pdf_generator_aniket-2.1.1.dist-info/entry_points.txt
pdf_generator_aniket-2.1.1.dist-info/top_level.txt
pdf_generator_aniket-2.1.1.dist-info/RECORD
