Metadata-Version: 2.2
Name: pdf-generator-aniket
Version: 2.1.1
Summary: A user-friendly PDF generation tool built with Python and Tkinter. Supports customizable pages, watermarks, text placement, color modes, and now allows setting a target PDF file size. Ideal for automating batch PDF creation with flexible options.
Home-page: https://github.com/Aniketc068/pdf_generator
Author: Aniket Chaturvedi
Author-email: chaturvedianiket007@gmail.com
Classifier: Programming Language :: Python :: 3
Classifier: Operating System :: Microsoft :: Windows
Requires-Python: >=3.7
License-File: LICENSE
Requires-Dist: reportlab
Requires-Dist: Pillow
Requires-Dist: pywin32
Requires-Dist: chardet
Dynamic: author
Dynamic: author-email
Dynamic: classifier
Dynamic: description
Dynamic: description-content-type
Dynamic: home-page
Dynamic: requires-dist
Dynamic: requires-python
Dynamic: summary
